Workbook

Sheet Input & Output (Basic)
A1: Input Field | B1: Value
A2: Vessel Purchase Date | B2: 46022
A3: Vessel Purchase Price | B3: 100000000
A4: Vessel Expect Life | B4: 25
A5: Vessel Residual Value | B5: 5000000
A6: Revenue per Day | B6: 50000
A7: Days of a Year | B7: 365
A8: Offhire Rate % | B8: 0.02
A9: Operating Expense (OpEx) per Day | B9: 10000
A10: Drydock CapEx Cost | B10: 5000000
A11: Drydock Frequency | B11: 5
A12: Upgrades CapEx Cost | B12: 500000
A13: Inflation Rate Assumption | B13: 0.03
A14: Discount Rate Assumption | B14: 0.1
A18: Output Field | B18: Value
A19: NPV | B19: =NPV($B$14,Calculation!$B$29:$AG$29)*(1+$B$14) -> 4143625.4
A20: IRR | B20: =IRR(Calculation!B29:AG29) -> 0.10585531
A24: Inflation Scenario | B24: Value
A25: Inflation Rate Best Case | B25: 0.01
A26: Inflation Rate Base Case | B26: 0.03
A27: Inflation Rate Worst Case | B27: 0.05

Sheet Calculation
A1: Assumptions
A2: Year | B2: ='Input & Output (Basic)'!$B$2 -> 46022 | C2: =EOMONTH(B2,12) -> 46387 | D2: =EOMONTH(C2,12) -> 46752 | E2: =EOMONTH(D2,12) -> 47118 | F2: =EOMONTH(E2,12) -> 47483 | G2: =EOMONTH(F2,12) -> 47848 | H2: =EOMONTH(G2,12) -> 48213 | I2: =EOMONTH(H2,12) -> 48579 | J2: =EOMONTH(I2,12) -> 48944 | ... AG2: =EOMONTH(AF2,12) -> 57345
A3: Vessel Age | B3: =ROUND((B$2-'Input & Output (Basic)'!$B$2)/365,0) -> 0 | C3: =ROUND((C$2-'Input & Output (Basic)'!$B$2)/365,0) -> 1 | D3: =ROUND((D$2-'Input & Output (Basic)'!$B$2)/365,0) -> 2 | E3: =ROUND((E$2-'Input & Output (Basic)'!$B$2)/365,0) -> 3 | F3: =ROUND((F$2-'Input & Output (Basic)'!$B$2)/365,0) -> 4 | G3: =ROUND((G$2-'Input & Output (Basic)'!$B$2)/365,0) -> 5 | H3: =ROUND((H$2-'Input & Output (Basic)'!$B$2)/365,0) -> 6 | I3: =ROUND((I$2-'Input & Output (Basic)'!$B$2)/365,0) -> 7 | ... AG3: =ROUND((AG$2-'Input & Output (Basic)'!$B$2)/365,0) -> 31
A4: Vessel Active? | B4: =AND( B$3<='Input & Output (Basic)'!$B$4, B$3<>0) -> FALSE | C4: =AND( C$3<='Input & Output (Basic)'!$B$4, C$3<>0) -> TRUE | D4: =AND( D$3<='Input & Output (Basic)'!$B$4, D$3<>0) -> TRUE | E4: =AND( E$3<='Input & Output (Basic)'!$B$4, E$3<>0) -> TRUE | F4: =AND( F$3<='Input & Output (Basic)'!$B$4, F$3<>0) -> TRUE | G4: =AND( G$3<='Input & Output (Basic)'!$B$4, G$3<>0) -> TRUE | H4: =AND( H$3<='Input & Output (Basic)'!$B$4, H$3<>0) -> TRUE | I4: =AND( I$3<='Input & Output (Basic)'!$B$4, I$3<>0) -> TRUE | ... AG4: =AND( AG$3<='Input & Output (Basic)'!$B$4, AG$3<>0) -> FALSE
A5: Drydock Year? | B5: =AND(MOD(B$3,5)=0, ('Input & Output (Basic)'!$B$4-B$3>=5), B$3<>0) -> FALSE | C5: =AND(MOD(C$3,5)=0, ('Input & Output (Basic)'!$B$4-C$3>=5), C$3<>0) -> FALSE | D5: =AND(MOD(D$3,5)=0, ('Input & Output (Basic)'!$B$4-D$3>=5), D$3<>0) -> FALSE | E5: =AND(MOD(E$3,5)=0, ('Input & Output (Basic)'!$B$4-E$3>=5), E$3<>0) -> FALSE | F5: =AND(MOD(F$3,5)=0, ('Input & Output (Basic)'!$B$4-F$3>=5), F$3<>0) -> FALSE | G5: =AND(MOD(G$3,5)=0, ('Input & Output (Basic)'!$B$4-G$3>=5), G$3<>0) -> TRUE | H5: =AND(MOD(H$3,5)=0, ('Input & Output (Basic)'!$B$4-H$3>=5), H$3<>0) -> FALSE | I5: =AND(MOD(I$3,5)=0, ('Input & Output (Basic)'!$B$4-I$3>=5), I$3<>0) -> FALSE | ... AG5: =AND(MOD(AG$3,5)=0, ('Input & Output (Basic)'!$B$4-AG$3>=5), AG$3<>0) -> FALSE
A6: Inflation Factor in Year t | B6: =(1+'Input & Output (Basic)'!$B$13)^B$3 -> 1 | C6: =(1+'Input & Output (Basic)'!$B$13)^C$3 -> 1.03 | D6: =(1+'Input & Output (Basic)'!$B$13)^D$3 -> 1.0609 | E6: =(1+'Input & Output (Basic)'!$B$13)^E$3 -> 1.092727 | F6: =(1+'Input & Output (Basic)'!$B$13)^F$3 -> 1.1255088 | G6: =(1+'Input & Output (Basic)'!$B$13)^G$3 -> 1.1592741 | H6: =(1+'Input & Output (Basic)'!$B$13)^H$3 -> 1.1940523 | I6: =(1+'Input & Output (Basic)'!$B$13)^I$3 -> 1.2298739 | ... AG6: =(1+'Input & Output (Basic)'!$B$13)^AG$3 -> 2.5000803
A7: Discount Rate Factor in Year t | B7: =(1+'Input & Output (Basic)'!$B$14)^B$3 -> 1 | C7: =(1+'Input & Output (Basic)'!$B$14)^C$3 -> 1.1 | D7: =(1+'Input & Output (Basic)'!$B$14)^D$3 -> 1.21 | E7: =(1+'Input & Output (Basic)'!$B$14)^E$3 -> 1.331 | F7: =(1+'Input & Output (Basic)'!$B$14)^F$3 -> 1.4641 | G7: =(1+'Input & Output (Basic)'!$B$14)^G$3 -> 1.61051 | H7: =(1+'Input & Output (Basic)'!$B$14)^H$3 -> 1.771561 | I7: =(1+'Input & Output (Basic)'!$B$14)^I$3 -> 1.9487171 | ... AG7: =(1+'Input & Output (Basic)'!$B$14)^AG$3 -> 19.194342
A8: Offhire Rate | B8: ='Input & Output (Basic)'!$B$8 -> 0.02 | C8: ='Input & Output (Basic)'!$B$8 -> 0.02 | D8: ='Input & Output (Basic)'!$B$8 -> 0.02 | E8: ='Input & Output (Basic)'!$B$8 -> 0.02 | F8: ='Input & Output (Basic)'!$B$8 -> 0.02 | G8: ='Input & Output (Basic)'!$B$8 -> 0.02 | H8: ='Input & Output (Basic)'!$B$8 -> 0.02 | I8: ='Input & Output (Basic)'!$B$8 -> 0.02 | ... AG8: ='Input & Output (Basic)'!$B$8 -> 0.02
A9: Days of the Year | B9: =MIN('Input & Output (Basic)'!$B$7,B$2-'Input & Output (Basic)'!$B$2) -> 0 | C9: =MIN('Input & Output (Basic)'!$B$7,C$2-'Input & Output (Basic)'!$B$2) -> 365 | D9: =MIN('Input & Output (Basic)'!$B$7,D$2-'Input & Output (Basic)'!$B$2) -> 365 | E9: =MIN('Input & Output (Basic)'!$B$7,E$2-'Input & Output (Basic)'!$B$2) -> 365 | F9: =MIN('Input & Output (Basic)'!$B$7,F$2-'Input & Output (Basic)'!$B$2) -> 365 | G9: =MIN('Input & Output (Basic)'!$B$7,G$2-'Input & Output (Basic)'!$B$2) -> 365 | H9: =MIN('Input & Output (Basic)'!$B$7,H$2-'Input & Output (Basic)'!$B$2) -> 365 | I9: =MIN('Input & Output (Basic)'!$B$7,I$2-'Input & Output (Basic)'!$B$2) -> 365 | ... AG9: =MIN('Input & Output (Basic)'!$B$7,AG$2-'Input & Output (Basic)'!$B$2) -> 365
A10: Daily Revenue Rate | B10: ='Input & Output (Basic)'!$B$6*B$4*(1-B$8) -> 0 | C10: ='Input & Output (Basic)'!$B$6*C$4*(1-C$8) -> 49000 | D10: ='Input & Output (Basic)'!$B$6*D$4*(1-D$8) -> 49000 | E10: ='Input & Output (Basic)'!$B$6*E$4*(1-E$8) -> 49000 | F10: ='Input & Output (Basic)'!$B$6*F$4*(1-F$8) -> 49000 | G10: ='Input & Output (Basic)'!$B$6*G$4*(1-G$8) -> 49000 | H10: ='Input & Output (Basic)'!$B$6*H$4*(1-H$8) -> 49000 | I10: ='Input & Output (Basic)'!$B$6*I$4*(1-I$8) -> 49000 | ... AG10: ='Input & Output (Basic)'!$B$6*AG$4*(1-AG$8) -> 0
A11: Daily OpEx Rate | B11: ='Input & Output (Basic)'!$B$9*B$4 -> 0 | C11: ='Input & Output (Basic)'!$B$9*C$4 -> 10000 | D11: ='Input & Output (Basic)'!$B$9*D$4 -> 10000 | E11: ='Input & Output (Basic)'!$B$9*E$4 -> 10000 | F11: ='Input & Output (Basic)'!$B$9*F$4 -> 10000 | G11: ='Input & Output (Basic)'!$B$9*G$4 -> 10000 | H11: ='Input & Output (Basic)'!$B$9*H$4 -> 10000 | I11: ='Input & Output (Basic)'!$B$9*I$4 -> 10000 | ... AG11: ='Input & Output (Basic)'!$B$9*AG$4 -> 0
A12: Daily OpEx Inflation Adjusted | B12: =B$11*B$6 -> 0 | C12: =C$11*C$6 -> 10300 | D12: =D$11*D$6 -> 10609 | E12: =E$11*E$6 -> 10927.27 | F12: =F$11*F$6 -> 11255.088 | G12: =G$11*G$6 -> 11592.741 | H12: =H$11*H$6 -> 11940.523 | I12: =I$11*I$6 -> 12298.739 | ... AG12: =AG$11*AG$6 -> 0
A13: Drydock Base | B13: ='Input & Output (Basic)'!$B$10*B5 -> 0 | C13: ='Input & Output (Basic)'!$B$10*C5 -> 0 | D13: ='Input & Output (Basic)'!$B$10*D5 -> 0 | E13: ='Input & Output (Basic)'!$B$10*E5 -> 0 | F13: ='Input & Output (Basic)'!$B$10*F5 -> 0 | G13: ='Input & Output (Basic)'!$B$10*G5 -> 5000000 | H13: ='Input & Output (Basic)'!$B$10*H5 -> 0 | I13: ='Input & Output (Basic)'!$B$10*I5 -> 0 | ... AG13: ='Input & Output (Basic)'!$B$10*AG5 -> 0
A14: Drydock Inflation Adjusted | B14: =B13*B$6 -> 0 | C14: =C13*C$6 -> 0 | D14: =D13*D$6 -> 0 | E14: =E13*E$6 -> 0 | F14: =F13*F$6 -> 0 | G14: =G13*G$6 -> 5796370.4 | H14: =H13*H$6 -> 0 | I14: =I13*I$6 -> 0 | ... AG14: =AG13*AG$6 -> 0
A15: Upgrades Base | B15: ='Input & Output (Basic)'!$B$12*B4 -> 0 | C15: ='Input & Output (Basic)'!$B$12*C4 -> 500000 | D15: ='Input & Output (Basic)'!$B$12*D4 -> 500000 | E15: ='Input & Output (Basic)'!$B$12*E4 -> 500000 | F15: ='Input & Output (Basic)'!$B$12*F4 -> 500000 | G15: ='Input & Output (Basic)'!$B$12*G4 -> 500000 | H15: ='Input & Output (Basic)'!$B$12*H4 -> 500000 | I15: ='Input & Output (Basic)'!$B$12*I4 -> 500000 | ... AG15: ='Input & Output (Basic)'!$B$12*AG4 -> 0
A16: Upgrades Inflation Adjusted | B16: =B15*B$6 -> 0 | C16: =C15*C$6 -> 515000 | D16: =D15*D$6 -> 530450 | E16: =E15*E$6 -> 546363.5 | F16: =F15*F$6 -> 562754.4 | G16: =G15*G$6 -> 579637.04 | H16: =H15*H$6 -> 597026.15 | I16: =I15*I$6 -> 614936.93 | ... AG16: =AG15*AG$6 -> 0
A18: Financials
A19: Total Revenue | B19: =B10*B9*B4 -> 0 | C19: =C10*C9*C4 -> 17885000 | D19: =D10*D9*D4 -> 17885000 | E19: =E10*E9*E4 -> 17885000 | F19: =F10*F9*F4 -> 17885000 | G19: =G10*G9*G4 -> 17885000 | H19: =H10*H9*H4 -> 17885000 | I19: =I10*I9*I4 -> 17885000 | ... AG19: =AG10*AG9*AG4 -> 0
A20: Total OpEx | B20: =B12*B9*B4 -> 0 | C20: =C12*C9*C4 -> 3759500 | D20: =D12*D9*D4 -> 3872285 | E20: =E12*E9*E4 -> 3988453.6 | F20: =F12*F9*F4 -> 4108107.2 | G20: =G12*G9*G4 -> 4231350.4 | H20: =H12*H9*H4 -> 4358290.9 | I20: =I12*I9*I4 -> 4489039.6 | ... AG20: =AG12*AG9*AG4 -> 0
A21: Drydock CapEx | B21: =B14 -> 0 | C21: =C14 -> 0 | D21: =D14 -> 0 | E21: =E14 -> 0 | F21: =F14 -> 0 | G21: =G14 -> 5796370.4 | H21: =H14 -> 0 | I21: =I14 -> 0 | ... AG21: =AG14 -> 0
A22: Upgrade CapEx | B22: =B16 -> 0 | C22: =C16 -> 515000 | D22: =D16 -> 530450 | E22: =E16 -> 546363.5 | F22: =F16 -> 562754.4 | G22: =G16 -> 579637.04 | H22: =H16 -> 597026.15 | I22: =I16 -> 614936.93 | ... AG22: =AG16 -> 0
A23: Total CapEx | B23: =SUBTOTAL(9,B21:B22) -> 0 | C23: =SUBTOTAL(9,C21:C22) -> 515000 | D23: =SUBTOTAL(9,D21:D22) -> 530450 | E23: =SUBTOTAL(9,E21:E22) -> 546363.5 | F23: =SUBTOTAL(9,F21:F22) -> 562754.4 | G23: =SUBTOTAL(9,G21:G22) -> 6376007.4 | H23: =SUBTOTAL(9,H21:H22) -> 597026.15 | I23: =SUBTOTAL(9,I21:I22) -> 614936.93 | ... AG23: =SUBTOTAL(9,AG21:AG22) -> 0
A24: Vessel Free Cash Flow | B24: =B19-B20-B23 -> 0 | C24: =C19-C20-C23 -> 13610500 | D24: =D19-D20-D23 -> 13482265 | E24: =E19-E20-E23 -> 13350183 | F24: =F19-F20-F23 -> 13214138 | G24: =G19-G20-G23 -> 7277642.2 | H24: =H19-H20-H23 -> 12929683 | I24: =I19-I20-I23 -> 12781023 | ... AG24: =AG19-AG20-AG23 -> 0
A26: Investments
A27: Vessel Purchase Price Base | B27: =IF(B$3=0,-'Input & Output (Basic)'!$B$3,0) -> -100000000 | C27: =IF(C$3=0,-'Input & Output (Basic)'!$B$3,0) -> 0 | D27: =IF(D$3=0,-'Input & Output (Basic)'!$B$3,0) -> 0 | E27: =IF(E$3=0,-'Input & Output (Basic)'!$B$3,0) -> 0 | F27: =IF(F$3=0,-'Input & Output (Basic)'!$B$3,0) -> 0 | G27: =IF(G$3=0,-'Input & Output (Basic)'!$B$3,0) -> 0 | H27: =IF(H$3=0,-'Input & Output (Basic)'!$B$3,0) -> 0 | I27: =IF(I$3=0,-'Input & Output (Basic)'!$B$3,0) -> 0 | ... AG27: =IF(AG$3=0,-'Input & Output (Basic)'!$B$3,0) -> 0
A28: Vessel Residual Value Base | B28: =IF(B$3='Input & Output (Basic)'!$B$4,'Input & Output (Basic)'!$B$5,0) -> 0 | C28: =IF(C$3='Input & Output (Basic)'!$B$4,'Input & Output (Basic)'!$B$5,0) -> 0 | D28: =IF(D$3='Input & Output (Basic)'!$B$4,'Input & Output (Basic)'!$B$5,0) -> 0 | E28: =IF(E$3='Input & Output (Basic)'!$B$4,'Input & Output (Basic)'!$B$5,0) -> 0 | F28: =IF(F$3='Input & Output (Basic)'!$B$4,'Input & Output (Basic)'!$B$5,0) -> 0 | G28: =IF(G$3='Input & Output (Basic)'!$B$4,'Input & Output (Basic)'!$B$5,0) -> 0 | H28: =IF(H$3='Input & Output (Basic)'!$B$4,'Input & Output (Basic)'!$B$5,0) -> 0 | I28: =IF(I$3='Input & Output (Basic)'!$B$4,'Input & Output (Basic)'!$B$5,0) -> 0 | ... AG28: =IF(AG$3='Input & Output (Basic)'!$B$4,'Input & Output (Basic)'!$B$5,0) -> 0
A29: Net Cash Flow | B29: =B24+B27+B28 -> -100000000 | C29: =C24+C27+C28 -> 13610500 | D29: =D24+D27+D28 -> 13482265 | E29: =E24+E27+E28 -> 13350183 | F29: =F24+F27+F28 -> 13214138 | G29: =G24+G27+G28 -> 7277642.2 | H29: =H24+H27+H28 -> 12929683 | I29: =I24+I27+I28 -> 12781023 | ... AG29: =AG24+AG27+AG28 -> 0
A31: Discounted Net Cash Flow | B31: =B29/B7 -> -100000000 | C31: =C29/C7 -> 12373182 | D31: =D29/D7 -> 11142368 | E31: =E29/E7 -> 10030190 | F31: =F29/F7 -> 9025434.4 | G31: =G29/G7 -> 4518843.2 | H31: =H29/H7 -> 7298469 | I31: =I29/I7 -> 6558685.9 | ... AG31: =AG29/AG7 -> 0

Sheet Sample Data for Testing
A1: Input Field | B1: TEU Size | C1: LWT | D1: Vessel Purchase Date | E1: Vessel Purchase Price | F1: Vessel Expect Life | G1: Vessel Residual Value | H1: Revenue per Day | I1: Days of a Year | J1: Offhire Rate % | K1: Operating Expense (OpEx) per Day | L1: Drydock CapEx Cost | M1: Drydock Frequency | N1: Upgrades CapEx Cost | O1: Inflation Rate Assumption | P1: Discount Rate Assumption | Q1: Engine | R1: CO2 Carbon Factor
A2: Sample Vessle #1 | B2: 7000 | C2: 12345 | D2: 44651 | E2: 80000000 | F2: 25 | G2: =C2*400 -> 4938000 | H2: 40000 | I2: 365 | J2: 0.02 | K2: 11000 | L2: 3950000 | M2: 5 | N2: 500000 | O2: 0.03 | P2: 0.1 | Q2: LNG DF | R2: 0.8
A3: Sample Vessle #2 | B3: 7000 | C3: 12345 | D3: =EOMONTH(D2,3) -> 44742 | E3: 80000000 | F3: 25 | G3: =C3*400 -> 4938000 | H3: 40000 | I3: 365 | J3: 0.02 | K3: 11000 | L3: 4000000 | M3: 5 | N3: 500000 | O3: 0.03 | P3: 0.1 | Q3: LNG DF | R3: 0.8
A4: Sample Vessle #3 | B4: 7000 | C4: 12500 | D4: =EOMONTH(D3,3) -> 44834 | E4: 80000000 | F4: 25 | G4: =C4*400 -> 5000000 | H4: 40000 | I4: 365 | J4: 0.02 | K4: 11000 | L4: 4500000 | M4: 5 | N4: 500000 | O4: 0.03 | P4: 0.1 | Q4: LNG DF | R4: 0.8
A5: Sample Vessle #4 | B5: 10000 | C5: 14280 | D5: 45107 | E5: 100000000 | F5: 25 | G5: =C5*400 -> 5712000 | H5: 50000 | I5: 365 | J5: 0.02 | K5: 10000 | L5: 5000000 | M5: 5 | N5: 500000 | O5: 0.03 | P5: 0.1 | Q5: Conventional | R5: 1.1
A6: Sample Vessle #5 | B6: 10000 | C6: 14280 | D6: 45107 | E6: 100000000 | F6: 25 | G6: =C6*400 -> 5712000 | H6: 50000 | I6: 365 | J6: 0.02 | K6: 10000 | L6: 5000000 | M6: 5 | N6: 500000 | O6: 0.03 | P6: 0.1 | Q6: Conventional | R6: 1.1
A7: Sample Vessle #6 | B7: 12000 | C7: 15340 | D7: 45382 | E7: 115000000 | F7: 25 | G7: =C7*400 -> 6136000 | H7: 54000 | I7: 365 | J7: 0.02 | K7: 10000 | L7: 4800000 | M7: 5 | N7: 500000 | O7: 0.03 | P7: 0.1 | Q7: Conventional | R7: 1.05
A8: Sample Vessle #7 | B8: 12000 | C8: 15440 | D8: 45397 | E8: 115000000 | F8: 25 | G8: =C8*400 -> 6176000 | H8: 54000 | I8: 365 | J8: 0.02 | K8: 10000 | L8: 4700000 | M8: 5 | N8: 500000 | O8: 0.03 | P8: 0.1 | Q8: Conventional | R8: 1.05
A9: Sample Vessle #8 | B9: 8000 | C9: - | D9: 45747 | E9: 9000000 | F9: 25 | G9: =C9*400 -> #VALUE! | H9: 45000 | I9: 365 | J9: 0.02 | K9: 10000 | L9: 5200000 | M9: 5 | N9: 500000 | O9: 0.03 | P9: 0.1 | Q9: LNG DF | R9: 0.78
A10: Sample Vessle #9 | B10: 8000 | C10: 13095 | D10: =EOMONTH(D9,3) -> 45838 | E10: 90000000 | F10: 25 | G10: =C10*400 -> 5238000 | H10: 45250 | I10: 365 | J10: 0.02 | K10: 10500 | L10: 5252000 | M10: 5 | N10: 500000 | O10: 0.03 | P10: 0.1 | Q10: LNG DF | R10: 0.78
A11: Sample Vessle #10 | B11: 8000 | C11: 13095 | D11: =EOMONTH(D10,3) -> 45930 | E11: 90000000 | F11: 25 | G11: =C11*400 -> 5238000 | H11: 45500 | I11: 365 | J11: 0.02 | K11: 10500 | L11: 5240000 | M11: 5 | N11: 500000 | O11: 0.03 | P11: 0.1 | Q11: LNG DF | R11: 0.78
